slack/__init__.py
slack/functions.py
slackmodule-0.0.1.dist-info/LICENSE
slackmodule-0.0.1.dist-info/METADATA
slackmodule-0.0.1.dist-info/WHEEL
slackmodule-0.0.1.dist-info/top_level.txt
slackmodule-0.0.1.dist-info/RECORD
