Metadata-Version: 2.1
Name: slackmodule
Version: 0.0.1
Summary: LOGEX specific slack package
Author: Jason Dsouza
Author-email: <m.a.lupulescu@gmail.com>
Keywords: python,slack,logex
Classifier: Development Status :: 3 - Alpha
Classifier: Intended Audience :: Education
Classifier: Programming Language :: Python :: 2
Classifier: Programming Language :: Python :: 3
Classifier: Operating System :: MacOS :: MacOS X
Classifier: Operating System :: Microsoft :: Windows
License-File: LICENSE
